h0lwin/__init__.py
h0lwin-1.0.1.dist-info/METADATA
h0lwin-1.0.1.dist-info/WHEEL
h0lwin-1.0.1.dist-info/top_level.txt
h0lwin-1.0.1.dist-info/RECORD
