Metadata-Version: 2.1
Name: h0lwin
Version: 1.0.1
Summary: A fun Python package that introduces H0lwin — a developer from Shiraz, Iran
Home-page: https://github.com/heroinsh/h0lwin
Author: H0lwin
Author-email: shayanqasmy88@gmail.com
Classifier: Programming Language :: Python :: 3
Classifier: Operating System :: OS Independent
Classifier: Intended Audience :: Developers
Classifier: License :: OSI Approved :: MIT License
Requires-Python: >=3.6
